tron_explorer/__init__.py
tron_explorer/account.py
tron_explorer/block.py
tron_explorer/data_map.py
tron_explorer/exceptions.py
tron_explorer/explore.py
tron_explorer/proposals.py
tron_explorer/smart_contract.py
tron_explorer/sr.py
tron_explorer/token_list.py
tron_explorer/token_single.py
tron_explorer/transaction.py
tron_explorer/utils.py
tron_explorer/test/__init__.py
tron_explorer/test/test_account_endpoints.py
tron_explorer/test/test_block_endpoints.py
tron_explorer/test/test_getting_properties.py
tron_explorer/test/test_proposal_endpoints.py
tron_explorer/test/test_smart_contracts_endpoints.py
tron_explorer/test/test_sr_endpoints.py
tron_explorer/test/test_token_endpoints.py
tron_explorer/test/test_transaction_endpoints.py
tron_explorer-1.0.0.dist-info/LICENCE.txt
tron_explorer-1.0.0.dist-info/METADATA
tron_explorer-1.0.0.dist-info/WHEEL
tron_explorer-1.0.0.dist-info/top_level.txt
tron_explorer-1.0.0.dist-info/RECORD
