Metadata-Version: 2.1
Name: tron-explorer
Version: 1.0.0
Summary: A Python Wrapper for tronscan.org REST API
Home-page: UNKNOWN
Author: Amirali Omidvar
Author-email: amirali.omidvar80@gmail.com
License: MIT
Platform: UNKNOWN
License-File: LICENCE.txt
